dbsamizdat/__init__.py
dbsamizdat/api.py
dbsamizdat/apps.py
dbsamizdat/django_api.py
dbsamizdat/exceptions.py
dbsamizdat/graphvizdot.py
dbsamizdat/libdb.py
dbsamizdat/libgraph.py
dbsamizdat/loader.py
dbsamizdat/models.py
dbsamizdat/samizdat.py
dbsamizdat/samtypes.py
dbsamizdat/util.py
dbsamizdat/management/commands/dbsamizdat.py
dbsamizdat/runner/__init__.py
dbsamizdat/runner/__main__.py
dbsamizdat/runner/cli.py
dbsamizdat/runner/commands.py
dbsamizdat/runner/context.py
dbsamizdat/runner/executor.py
dbsamizdat/runner/helpers.py
dbsamizdat/runner/types.py
dbsamizdapper-0.1.1.dist-info/METADATA
dbsamizdapper-0.1.1.dist-info/WHEEL
dbsamizdapper-0.1.1.dist-info/licenses/LICENSE.txt
dbsamizdapper-0.1.1.dist-info/RECORD
