Metadata-Version: 2.4
Name: dbsamizdapper
Version: 0.1.1
Summary: Blissfully naive PostgreSQL database object manager for views, materialized views, functions, and triggers
Project-URL: Homepage, https://github.com/catalpainternational/dbsamizdapper
Project-URL: Documentation, https://github.com/catalpainternational/dbsamizdapper#readme
Project-URL: Repository, https://github.com/catalpainternational/dbsamizdapper
Project-URL: Issues, https://github.com/catalpainternational/dbsamizdapper/issues
Author-email: Josh Brooks <josh@catalpa.io>
License:                     GNU GENERAL PUBLIC LICENSE
License-File: LICENSE.txt
Keywords: database,django,materialized-views,postgresql,sql,views
Classifier: Development Status :: 4 - Beta
Classifier: Intended Audience :: Developers
Classifier: License :: OSI Approved
Classifier: Programming Language :: Python :: 3.12
Classifier: Programming Language :: Python :: 3.13
Classifier: Programming Language :: Python :: 3.14
Classifier: Topic :: Database
Requires-Python: >=3.12
Requires-Dist: pytest-cov>=7.0.0
Requires-Dist: toposort>=1.10
Provides-Extra: django
Requires-Dist: django-stubs>=4.2.0; extra == 'django'
Requires-Dist: django<5.0,>=4.2; extra == 'django'
Provides-Extra: psycopg3
Requires-Dist: psycopg[binary]>=3.1.9; extra == 'psycopg3'
